src/__init__.py
src/client.py
lgnashold_rayank_test_package-0.0.1.dist-info/METADATA
lgnashold_rayank_test_package-0.0.1.dist-info/WHEEL
lgnashold_rayank_test_package-0.0.1.dist-info/RECORD
