Metadata-Version: 2.1
Name: lgnashold_rayank_test_package
Version: 0.0.1
Summary: Python SDK for playground project
Author: Langston Nashold, Rayank Krishnan
